mentalweather/WeatherRegression.py
mentalweather/__init__.py
mentalweather/app.py
mentalweather/eda.py
mentalweather/make_weather_history_data.py
mentalweather-0.0.2.dist-info/LICENCE.txt
mentalweather-0.0.2.dist-info/METADATA
mentalweather-0.0.2.dist-info/WHEEL
mentalweather-0.0.2.dist-info/top_level.txt
mentalweather-0.0.2.dist-info/RECORD
