Metadata-Version: 2.1
Name: mentalweather
Version: 0.0.2
Summary: A package including the analysis of relationship between mental disease and weather and an application based on the ML model
Author-email: Shih-Yen Hung <syhung@gapp.nthu.edu.tw>
Project-URL: Homepage, https://github.com/ShihYenHung/SCE_SY
Project-URL: Issues, https://github.com/ShihYenHung/SCE_SY/issues
Classifier: Programming Language :: Python :: 3
Classifier: License :: OSI Approved :: MIT License
Classifier: Operating System :: OS Independent
Requires-Python: >=3.11
License-File: LICENCE.txt
